executorx/__init__.py
executorx/__version__.py
executorx/threading.py
executorx/utils.py
executorx/addons/__init__.py
executorx/addons/progress.py
executorx/addons/throttle.py
executorx/addons/var_registry.py
executorx/addons/worker_id.py
executorx/foundation/__init__.py
executorx/foundation/addon.py
executorx/foundation/basic_immediate_executor.py
executorx/foundation/executor_identifier.py
executorx/futures/__init__.py
executorx/futures/executors.py
executorx/futures/start_all_workers.py
ExecutorX-1.1.0.dist-info/LICENSE
ExecutorX-1.1.0.dist-info/METADATA
ExecutorX-1.1.0.dist-info/WHEEL
ExecutorX-1.1.0.dist-info/top_level.txt
ExecutorX-1.1.0.dist-info/RECORD
